d8s_algorithms/__init__.py
d8s_algorithms/algorithms.py
d8s_algorithms/algorithms_temp_utils.py
tests/__init__.py
tests/test_algorithms.py
d8s_algorithms-0.7.0.dist-info/COPYING
d8s_algorithms-0.7.0.dist-info/COPYING.LESSER
d8s_algorithms-0.7.0.dist-info/METADATA
d8s_algorithms-0.7.0.dist-info/WHEEL
d8s_algorithms-0.7.0.dist-info/top_level.txt
d8s_algorithms-0.7.0.dist-info/zip-safe
d8s_algorithms-0.7.0.dist-info/RECORD
